templates.py
templates.py-1.0.1.dist-info/LICENSE
templates.py-1.0.1.dist-info/METADATA
templates.py-1.0.1.dist-info/WHEEL
templates.py-1.0.1.dist-info/top_level.txt
templates.py-1.0.1.dist-info/RECORD
