Metadata-Version: 2.1
Name: templates.py
Version: 1.0.1
Summary: Simple function templating for Python.
Author: ZeroIntensity
Author-email: <zintensitydev@gmail.com>
License: MIT
Keywords: python,templating,templates,generics
Platform: UNKNOWN
Classifier: Programming Language :: Python :: 3.6
Classifier: Programming Language :: Python :: 3.7
Classifier: Programming Language :: Python :: 3.8
Classifier: Programming Language :: Python :: 3.9
Classifier: Programming Language :: Python :: 3.10
Classifier: Programming Language :: Python :: 3.11
License-File: LICENSE
Requires-Dist: typing-extensions
